{
  "drawNumber": 1248,
  "date": "1975-07-26",
  "results": [
    {
      "position": 1,
      "winningNumber": "038375",
      "prizeAmount": 200000.0
    },
    {
      "position": 2,
      "winningNumber": "010763",
      "prizeAmount": 8000.0
    },
    {
      "position": 3,
      "winningNumber": "056272",
      "prizeAmount": 5000.0
    },
    {
      "position": 4,
      "winningNumber": "055648",
      "prizeAmount": 4000.0
    },
    {
      "position": 5,
      "winningNumber": "023825",
      "prizeAmount": 2000.0
    }
  ]
}