{
  "drawNumber": 1283,
  "date": "1975-12-06",
  "results": [
    {
      "position": 1,
      "winningNumber": "000019",
      "prizeAmount": 200000.0
    },
    {
      "position": 2,
      "winningNumber": "056636",
      "prizeAmount": 8000.0
    },
    {
      "position": 3,
      "winningNumber": "019783",
      "prizeAmount": 5000.0
    },
    {
      "position": 4,
      "winningNumber": "051126",
      "prizeAmount": 4000.0
    },
    {
      "position": 5,
      "winningNumber": "026129",
      "prizeAmount": 2000.0
    }
  ]
}