{
  "drawNumber": 1529,
  "date": "1978-07-19",
  "results": [
    {
      "position": 1,
      "winningNumber": "015072",
      "prizeAmount": 200000.0
    },
    {
      "position": 2,
      "winningNumber": "038879",
      "prizeAmount": 8000.0
    },
    {
      "position": 3,
      "winningNumber": "006382",
      "prizeAmount": 5000.0
    },
    {
      "position": 4,
      "winningNumber": "005067",
      "prizeAmount": 4000.0
    },
    {
      "position": 5,
      "winningNumber": "050202",
      "prizeAmount": 2000.0
    }
  ]
}