{
  "drawNumber": 2054,
  "date": "1984-03-14",
  "results": [
    {
      "position": 1,
      "winningNumber": "053456",
      "prizeAmount": 200000.0
    },
    {
      "position": 2,
      "winningNumber": "046751",
      "prizeAmount": 8000.0
    },
    {
      "position": 3,
      "winningNumber": "028310",
      "prizeAmount": 5000.0
    },
    {
      "position": 4,
      "winningNumber": "029132",
      "prizeAmount": 4000.0
    },
    {
      "position": 5,
      "winningNumber": "004166",
      "prizeAmount": 2000.0
    }
  ]
}