{
  "drawNumber": 2851,
  "date": "1993-06-05",
  "results": [
    {
      "position": 1,
      "winningNumber": "056494",
      "prizeAmount": 200000.0
    },
    {
      "position": 2,
      "winningNumber": "027943",
      "prizeAmount": 8000.0
    },
    {
      "position": 3,
      "winningNumber": "049475",
      "prizeAmount": 5000.0
    },
    {
      "position": 4,
      "winningNumber": "001804",
      "prizeAmount": 4000.0
    },
    {
      "position": 5,
      "winningNumber": "022103",
      "prizeAmount": 2000.0
    }
  ]
}