{
  "drawNumber": 3996,
  "date": "2005-12-28",
  "results": [
    {
      "position": 1,
      "winningNumber": "071205",
      "prizeAmount": 100000.0
    },
    {
      "position": 2,
      "winningNumber": "001391",
      "prizeAmount": 6000.0
    },
    {
      "position": 3,
      "winningNumber": "006518",
      "prizeAmount": 4000.0
    },
    {
      "position": 4,
      "winningNumber": "050752",
      "prizeAmount": 3000.0
    },
    {
      "position": 5,
      "winningNumber": "053309",
      "prizeAmount": 2000.0
    }
  ]
}