{
  "drawNumber": 4728,
  "date": "2013-01-16",
  "results": [
    {
      "position": 1,
      "winningNumber": "027676",
      "prizeAmount": 250000.0
    },
    {
      "position": 2,
      "winningNumber": "003704",
      "prizeAmount": 16300.0
    },
    {
      "position": 3,
      "winningNumber": "003815",
      "prizeAmount": 15500.0
    },
    {
      "position": 4,
      "winningNumber": "006990",
      "prizeAmount": 15000.0
    },
    {
      "position": 5,
      "winningNumber": "035640",
      "prizeAmount": 13768.0
    }
  ]
}