{
  "drawNumber": 5543,
  "date": "2021-03-03",
  "results": [
    {
      "position": 1,
      "winningNumber": "028040",
      "prizeAmount": 500000.0
    },
    {
      "position": 2,
      "winningNumber": "020530",
      "prizeAmount": 27000.0
    },
    {
      "position": 3,
      "winningNumber": "043409",
      "prizeAmount": 24000.0
    },
    {
      "position": 4,
      "winningNumber": "007780",
      "prizeAmount": 19000.0
    },
    {
      "position": 5,
      "winningNumber": "009047",
      "prizeAmount": 18329.0
    }
  ]
}