{
  "drawNumber": 1829,
  "date": "1981-10-07",
  "results": [
    {
      "position": 1,
      "winningNumber": "011374",
      "prizeAmount": 200000.0
    },
    {
      "position": 2,
      "winningNumber": "053522",
      "prizeAmount": 8000.0
    },
    {
      "position": 3,
      "winningNumber": "002448",
      "prizeAmount": 5000.0
    },
    {
      "position": 4,
      "winningNumber": "065514",
      "prizeAmount": 4000.0
    },
    {
      "position": 5,
      "winningNumber": "038460",
      "prizeAmount": 2000.0
    }
  ]
}