{
  "drawNumber": 2080,
  "date": "1984-06-30",
  "results": [
    {
      "position": 1,
      "winningNumber": "034732",
      "prizeAmount": 200000.0
    },
    {
      "position": 2,
      "winningNumber": "044285",
      "prizeAmount": 8000.0
    },
    {
      "position": 3,
      "winningNumber": "022847",
      "prizeAmount": 5000.0
    },
    {
      "position": 4,
      "winningNumber": "035396",
      "prizeAmount": 4000.0
    },
    {
      "position": 5,
      "winningNumber": "024682",
      "prizeAmount": 2000.0
    }
  ]
}