{
  "drawNumber": 3766,
  "date": "2003-09-06",
  "results": [
    {
      "position": 1,
      "winningNumber": "063454",
      "prizeAmount": 100000.0
    },
    {
      "position": 2,
      "winningNumber": "034118",
      "prizeAmount": 6000.0
    },
    {
      "position": 3,
      "winningNumber": "023995",
      "prizeAmount": 4000.0
    },
    {
      "position": 4,
      "winningNumber": "024599",
      "prizeAmount": 3000.0
    },
    {
      "position": 5,
      "winningNumber": "001184",
      "prizeAmount": 2000.0
    }
  ]
}