{
  "drawNumber": 4020,
  "date": "2006-03-22",
  "results": [
    {
      "position": 1,
      "winningNumber": "036350",
      "prizeAmount": 200000.0
    },
    {
      "position": 2,
      "winningNumber": "054586",
      "prizeAmount": 12000.0
    },
    {
      "position": 3,
      "winningNumber": "038424",
      "prizeAmount": 8000.0
    },
    {
      "position": 4,
      "winningNumber": "022459",
      "prizeAmount": 6000.0
    },
    {
      "position": 5,
      "winningNumber": "037926",
      "prizeAmount": 4000.0
    }
  ]
}