{
  "drawNumber": 4121,
  "date": "2007-03-14",
  "results": [
    {
      "position": 1,
      "winningNumber": "003812",
      "prizeAmount": 200000.0
    },
    {
      "position": 2,
      "winningNumber": "071567",
      "prizeAmount": 12000.0
    },
    {
      "position": 3,
      "winningNumber": "006850",
      "prizeAmount": 8000.0
    },
    {
      "position": 4,
      "winningNumber": "073864",
      "prizeAmount": 6000.0
    },
    {
      "position": 5,
      "winningNumber": "052106",
      "prizeAmount": 4000.0
    }
  ]
}