{
  "drawNumber": 425,
  "date": "1966-12-31",
  "results": [
    {
      "position": 1,
      "winningNumber": "013275",
      "prizeAmount": 200000.0
    },
    {
      "position": 2,
      "winningNumber": "023618",
      "prizeAmount": 8000.0
    },
    {
      "position": 3,
      "winningNumber": "019841",
      "prizeAmount": 5000.0
    },
    {
      "position": 4,
      "winningNumber": "019189",
      "prizeAmount": 4000.0
    },
    {
      "position": 5,
      "winningNumber": "012965",
      "prizeAmount": 2000.0
    }
  ]
}