{
  "drawNumber": 4539,
  "date": "2011-03-26",
  "results": [
    {
      "position": 1,
      "winningNumber": "044136",
      "prizeAmount": 200000.0
    },
    {
      "position": 2,
      "winningNumber": "075677",
      "prizeAmount": 4000.0
    },
    {
      "position": 3,
      "winningNumber": "075431",
      "prizeAmount": 3000.0
    },
    {
      "position": 4,
      "winningNumber": "024726",
      "prizeAmount": 2470.0
    },
    {
      "position": 5,
      "winningNumber": "068687",
      "prizeAmount": 2000.0
    }
  ]
}