{
  "drawNumber": 695,
  "date": "1969-09-06",
  "results": [
    {
      "position": 1,
      "winningNumber": "008122",
      "prizeAmount": 200000.0
    },
    {
      "position": 2,
      "winningNumber": "003754",
      "prizeAmount": 8000.0
    },
    {
      "position": 3,
      "winningNumber": "003613",
      "prizeAmount": 5000.0
    },
    {
      "position": 4,
      "winningNumber": "001976",
      "prizeAmount": 4000.0
    },
    {
      "position": 5,
      "winningNumber": "036094",
      "prizeAmount": 2000.0
    }
  ]
}