{
  "drawNumber": 803,
  "date": "1970-10-07",
  "results": [
    {
      "position": 1,
      "winningNumber": "037365",
      "prizeAmount": 200000.0
    },
    {
      "position": 2,
      "winningNumber": "034241",
      "prizeAmount": 8000.0
    },
    {
      "position": 3,
      "winningNumber": "049837",
      "prizeAmount": 5000.0
    },
    {
      "position": 4,
      "winningNumber": "048697",
      "prizeAmount": 4000.0
    },
    {
      "position": 5,
      "winningNumber": "042768",
      "prizeAmount": 2000.0
    }
  ]
}